setup.py
EstimationTools.egg-info/PKG-INFO
EstimationTools.egg-info/SOURCES.txt
EstimationTools.egg-info/dependency_links.txt
EstimationTools.egg-info/entry_points.txt
EstimationTools.egg-info/top_level.txt
estimationtools/__init__.py
estimationtools/burndownchart.py
estimationtools/hoursinplaceeditor.py
estimationtools/hoursremaining.py
estimationtools/utils.py
estimationtools/workloadchart.py
estimationtools/htdocs/jquery-1.2.3.min.js
estimationtools/htdocs/jquery.jeditable.js
estimationtools/htdocs/jquery.jeditable.mini.js
estimationtools/templates/edithours.html
estimationtools/tests/__init__.py
estimationtools/tests/burndownchart.py
estimationtools/tests/hoursremaining.py
estimationtools/tests/utils.py
estimationtools/tests/workloadchart.py