Metadata-Version: 1.0
Name: EstimationTools
Version: 0.4.5
Summary: Trac plugin for visualizing and quick editing of effort estimations
Home-page: UNKNOWN
Author: Joachim Hoessler
Author-email: hoessler@gmail.com
License: BSD
Platform: UNKNOWN
